PyTetrys/__init__.py
PyTetrys/constantes.py
PyTetrys/pecas.py
pytetrys-0.0.4.dist-info/LICENSE
pytetrys-0.0.4.dist-info/METADATA
pytetrys-0.0.4.dist-info/WHEEL
pytetrys-0.0.4.dist-info/top_level.txt
pytetrys-0.0.4.dist-info/RECORD
